ytilities/__init__.py
ytilities/classes.py
ytilities/lists.py
ytilities/misc.py
ytilities/numbers.py
ytilities/paths.py
ytilities/system.py
ytilities/types.py
ytilities-0.1.1.dist-info/METADATA
ytilities-0.1.1.dist-info/WHEEL
ytilities-0.1.1.dist-info/RECORD
