Metadata-Version: 2.1
Name: ytilities
Version: 0.1.1
Summary: 
Author: Anthony Mugendi
Author-email: ngurumugz@gmail.com
Requires-Python: >=3.9,<4.0
Classifier: Programming Language :: Python :: 3
Classifier: Programming Language :: Python :: 3.9
Classifier: Programming Language :: Python :: 3.10
Classifier: Programming Language :: Python :: 3.11
Requires-Dist: numpy (>=1.24.3,<2.0.0)
